pybdm/__init__.py
pybdm/algorithms.py
pybdm/bdm.py
pybdm/encoding.py
pybdm/exceptions.py
pybdm/options.py
pybdm/partitions.py
pybdm/utils.py
pybdm/ctmdata/__init__.py
pybdm/ctmdata/ctm-b2-d12.pkl.gz
pybdm/ctmdata/ctm-b2-d4x4.pkl.gz
pybdm/ctmdata/ctm-b4-d12.pkl.gz
pybdm/ctmdata/ctm-b5-d12.pkl.gz
pybdm/ctmdata/ctm-b6-d12.pkl.gz
pybdm/ctmdata/ctm-b9-d12.pkl.gz
pybdm/ctmdata/__pycache__/__init__.cpython-35.pyc
pybdm/ctmdata/__pycache__/__init__.cpython-36.pyc
pybdm/ctmdata/__pycache__/__init__.cpython-37.pyc
pybdm-0.1.0.dist-info/AUTHORS.rst
pybdm-0.1.0.dist-info/LICENSE
pybdm-0.1.0.dist-info/METADATA
pybdm-0.1.0.dist-info/WHEEL
pybdm-0.1.0.dist-info/top_level.txt
pybdm-0.1.0.dist-info/RECORD
