Metadata-Version: 2.1
Name: pybdm
Version: 0.1.0
Summary: Python implementation of block decomposition method for approximating algorithmic complexity.
Home-page: https://github.com/sztal/pybdm
Author: Szymon Talaga
Maintainer: Szymon Talaga
Maintainer-email: stalaga@protonmail.com
License: MIT
Keywords: bdm,ctm,aid,algorithmic information,algorithmic information dynamics,algorithmic complexity,kolmogorov complexity,k-complexity,description length,block decomposition method,coding theorem method,algorithmic information theory
Platform: UNKNOWN
Classifier: Development Status :: 2 - Pre-Alpha
Classifier: Intended Audience :: Developers
Classifier: License :: OSI Approved :: MIT License
Classifier: Natural Language :: English
Classifier: Programming Language :: Python :: 3
Classifier: Programming Language :: Python :: 3.5
Classifier: Programming Language :: Python :: 3.6
Classifier: Programming Language :: Python :: 3.7
Classifier: Programming Language :: Python :: Implementation :: PyPy
Requires-Dist: numpy (>=1.15.4)
